usd_search_client/LICENSE.md
usd_search_client/__init__.py
usd_search_client/api/__init__.py
usd_search_client/api/ags_asset_graph_api.py
usd_search_client/api/ags_scene_graph_api.py
usd_search_client/api/ags_spatial_graph_api.py
usd_search_client/api/ai_search_api.py
usd_search_client/api/asset_api.py
usd_search_client/api/default_api.py
usd_search_client/api/images_api.py
usd_search_client/api/indexing_status_api.py
usd_search_client/api/plugins_api.py
usd_search_client/api/storage_backend_api.py
usd_search_client/api_client.py
usd_search_client/api_response.py
usd_search_client/configuration.py
usd_search_client/exceptions.py
usd_search_client/main/__init__.py
usd_search_client/main/models.py
usd_search_client/models/__init__.py
usd_search_client/models/ags_asset_data.py
usd_search_client/models/asset.py
usd_search_client/models/asset_graph.py
usd_search_client/models/asset_relationship.py
usd_search_client/models/asset_storage_backend_info.py
usd_search_client/models/available_storage_clients.py
usd_search_client/models/axis.py
usd_search_client/models/backend_status_type.py
usd_search_client/models/created_date_seconds.py
usd_search_client/models/deep_search_search_request.py
usd_search_client/models/deep_search_search_request_v2.py
usd_search_client/models/deepsearch_api_routers_v2_models_search_result.py
usd_search_client/models/deepsearch_api_search_backend_models_search_result.py
usd_search_client/models/deleted_date_seconds.py
usd_search_client/models/edge_type.py
usd_search_client/models/empty.py
usd_search_client/models/event.py
usd_search_client/models/event_mapping.py
usd_search_client/models/field_score_config.py
usd_search_client/models/hash_type.py
usd_search_client/models/hash_value.py
usd_search_client/models/http_validation_error.py
usd_search_client/models/hybrid_text_config.py
usd_search_client/models/job_item_type.py
usd_search_client/models/key_value_pair.py
usd_search_client/models/location_inner.py
usd_search_client/models/metadata.py
usd_search_client-1.2.0.dist-info/METADATA
usd_search_client-1.2.0.dist-info/WHEEL
usd_search_client-1.2.0.dist-info/licenses/LICENSE.md
usd_search_client-1.2.0.dist-info/RECORD
